{
  "$schema": "https://turborepo.com/schema.json",
  "ui": "tui",
  "tasks": {
    "build": {
      "dependsOn": ["^build"],
      "inputs": ["$TURBO_DEFAULT$", ".env*"],
      "outputs": [".next/**", "!.next/cache/**", "dist/**"]
    },
    "start": {
      "cache": false,
      "persistent": true
    },
    "dev": {
      "cache": false,
      "persistent": true
    },
    "console": {
      "cache": false
    },
    "install-deps": {
      "inputs": ["poetry.lock", "pyproject.toml", "package.json", "package-lock.json"],
      "cache": true
    },
    "lint": {
      "dependsOn": ["^lint"]
    },
    "check-types": {
      "dependsOn": ["^check-types"]
    }
  }
}
